LICENSE
README.md
pyproject.toml
setup.py
gemlite/__init__.py
gemlite/bitpack.py
gemlite/core.py
gemlite/dtypes.py
gemlite/helper.py
gemlite/quant_utils.py
gemlite.egg-info/PKG-INFO
gemlite.egg-info/SOURCES.txt
gemlite.egg-info/dependency_links.txt
gemlite.egg-info/requires.txt
gemlite.egg-info/top_level.txt
gemlite/configs/4090.json
gemlite/configs/5090.json
gemlite/configs/6000_ada.json
gemlite/configs/a100.json
gemlite/configs/a40.json
gemlite/configs/a6000.json
gemlite/configs/h100.json
gemlite/configs/l40.json
gemlite/configs/l40s.json
gemlite/configs/mi300x.json
gemlite/triton_kernels/__init__.py
gemlite/triton_kernels/config.py
gemlite/triton_kernels/gemm_kernels.py
gemlite/triton_kernels/gemm_splitK_kernels.py
gemlite/triton_kernels/gemm_splitK_persistent_kernels.py
gemlite/triton_kernels/gemv_kernels.py
gemlite/triton_kernels/gemv_revsplitK_kernels.py
gemlite/triton_kernels/gemv_splitK_kernels.py
gemlite/triton_kernels/utils.py
tests/test_gemlitelineartriton.py
tests/test_mxfp.py