Metadata-Version: 2.1
Name: gemlite
Version: 0.5.1.post1
Home-page: https://github.com/mobiusml/gemlite/
Author: Dr. Hicham Badri
Author-email: hicham@mobiuslabs.com
License: Apache 2
License-File: LICENSE
Requires-Dist: numpy
Requires-Dist: tqdm
